{"nodes": [{"id": "target_business_rules_doc", "label": "Target Business Rules", "file_type": "document", "source_file": "_reversa_sdd/migration/target_business_rules.md", "source_location": "10", "source_url": null, "captured_at": null, "author": null, "contributor": null}, {"id": "br_migrar_001", "label": "BR-MIGRAR-001 filtro company_id RLS", "file_type": "document", "source_file": "_reversa_sdd/migration/target_business_rules.md", "source_location": "23", "source_url": null, "captured_at": null, "author": null, "contributor": null}, {"id": "br_migrar_002", "label": "BR-MIGRAR-002 company_id via useAuth", "file_type": "document", "source_file": "_reversa_sdd/migration/target_business_rules.md", "source_location": "24", "source_url": null, "captured_at": null, "author": null, "contributor": null}, {"id": "br_migrar_014", "label": "BR-MIGRAR-014 checkout RPC complete_appointment", "file_type": "document", "source_file": "_reversa_sdd/migration/target_business_rules.md", "source_location": "41", "source_url": null, "captured_at": null, "author": null, "contributor": null}, {"id": "br_migrar_029", "label": "BR-MIGRAR-029 finalizacao fila atomica RPC", "file_type": "document", "source_file": "_reversa_sdd/migration/target_business_rules.md", "source_location": "61", "source_url": null, "captured_at": null, "author": null, "contributor": null}, {"id": "br_migrar_034", "label": "BR-MIGRAR-034 filtro professional_id financeiro", "file_type": "document", "source_file": "_reversa_sdd/migration/target_business_rules.md", "source_location": "71", "source_url": null, "captured_at": null, "author": null, "contributor": null}, {"id": "br_migrar_048", "label": "BR-MIGRAR-048 onboarding_progress source of truth", "file_type": "document", "source_file": "_reversa_sdd/migration/target_business_rules.md", "source_location": "90", "source_url": null, "captured_at": null, "author": null, "contributor": null}, {"id": "br_migrar_054", "label": "BR-MIGRAR-054 lixeira 30 dias restore RPC", "file_type": "document", "source_file": "_reversa_sdd/migration/target_business_rules.md", "source_location": "106", "source_url": null, "captured_at": null, "author": null, "contributor": null}, {"id": "br_descartar_001", "label": "BR-DESCARTAR-001 fallback checkout client-side", "file_type": "document", "source_file": "_reversa_sdd/migration/target_business_rules.md", "source_location": "121", "source_url": null, "captured_at": null, "author": null, "contributor": null}, {"id": "br_descartar_002", "label": "BR-DESCARTAR-002 finalizacao fila client-side", "file_type": "document", "source_file": "_reversa_sdd/migration/target_business_rules.md", "source_location": "122", "source_url": null, "captured_at": null, "author": null, "contributor": null}, {"id": "br_humana_004", "label": "BR-HUMANA-004 timeout calling 5min", "file_type": "document", "source_file": "_reversa_sdd/migration/target_business_rules.md", "source_location": "137", "source_url": null, "captured_at": null, "author": null, "contributor": null}], "edges": [{"source": "br_migrar_014", "target": "rpc_complete_appointment", "relation": "references", "confidence": "EXTRACTED", "confidence_score": 1.0, "source_file": "_reversa_sdd/migration/target_business_rules.md", "source_location": "41", "weight": 1.0}, {"source": "br_migrar_029", "target": "rpc_finish_queue_entry", "relation": "references", "confidence": "EXTRACTED", "confidence_score": 1.0, "source_file": "_reversa_sdd/migration/target_business_rules.md", "source_location": "61", "weight": 1.0}, {"source": "br_descartar_001", "target": "agenda_r11_complete_appointment", "relation": "rationale_for", "confidence": "INFERRED", "confidence_score": 0.85, "source_file": "_reversa_sdd/migration/target_business_rules.md", "source_location": "121", "weight": 1.0}, {"source": "br_descartar_002", "target": "agenda_r19_queue_client_side", "relation": "rationale_for", "confidence": "EXTRACTED", "confidence_score": 1.0, "source_file": "_reversa_sdd/migration/target_business_rules.md", "source_location": "122", "weight": 1.0}, {"source": "br_descartar_002", "target": "rpc_finish_queue_entry", "relation": "conceptually_related_to", "confidence": "EXTRACTED", "confidence_score": 1.0, "source_file": "_reversa_sdd/migration/target_business_rules.md", "source_location": "122", "weight": 1.0}, {"source": "br_migrar_048", "target": "onboarding_dual_system", "relation": "semantically_similar_to", "confidence": "EXTRACTED", "confidence_score": 1.0, "source_file": "_reversa_sdd/migration/target_business_rules.md", "source_location": "90", "weight": 1.0}, {"source": "br_humana_004", "target": "queue_entry_aggregate", "relation": "conceptually_related_to", "confidence": "EXTRACTED", "confidence_score": 1.0, "source_file": "_reversa_sdd/migration/target_business_rules.md", "source_location": "137", "weight": 1.0}], "hyperedges": [{"id": "atomic_operations_migration", "label": "Operacoes atomicas migradas para RPC", "nodes": ["br_migrar_014", "br_migrar_029", "br_descartar_001", "br_descartar_002", "rpc_complete_appointment", "rpc_finish_queue_entry"], "relation": "form", "confidence": "EXTRACTED", "confidence_score": 1.0, "source_file": "_reversa_sdd/migration/target_business_rules.md"}]}