{"nodes": [{"id": "c_users_user_downloads_rhian_lepore_main_reversa_sdd_sdd_clients_crm_md", "label": "clients-crm.md", "file_type": "document", "source_file": "C:\\Users\\User\\Downloads\\Rhian-Lepore-main\\_reversa_sdd\\sdd\\clients-crm.md", "source_location": "L1"}, {"id": "sdd_clients_crm_clientes_e_crm_clients_crm", "label": "Clientes e CRM (clients-crm)", "file_type": "document", "source_file": "C:\\Users\\User\\Downloads\\Rhian-Lepore-main\\_reversa_sdd\\sdd\\clients-crm.md", "source_location": "L1"}, {"id": "sdd_clients_crm_vis_o_geral", "label": "Vis\u00e3o Geral", "file_type": "document", "source_file": "C:\\Users\\User\\Downloads\\Rhian-Lepore-main\\_reversa_sdd\\sdd\\clients-crm.md", "source_location": "L3"}, {"id": "sdd_clients_crm_responsabilidades", "label": "Responsabilidades", "file_type": "document", "source_file": "C:\\Users\\User\\Downloads\\Rhian-Lepore-main\\_reversa_sdd\\sdd\\clients-crm.md", "source_location": "L6"}, {"id": "sdd_clients_crm_interface", "label": "Interface", "file_type": "document", "source_file": "C:\\Users\\User\\Downloads\\Rhian-Lepore-main\\_reversa_sdd\\sdd\\clients-crm.md", "source_location": "L19"}, {"id": "sdd_clients_crm_entradas", "label": "Entradas", "file_type": "document", "source_file": "C:\\Users\\User\\Downloads\\Rhian-Lepore-main\\_reversa_sdd\\sdd\\clients-crm.md", "source_location": "L21"}, {"id": "sdd_clients_crm_sa_das", "label": "Sa\u00eddas", "file_type": "document", "source_file": "C:\\Users\\User\\Downloads\\Rhian-Lepore-main\\_reversa_sdd\\sdd\\clients-crm.md", "source_location": "L34"}, {"id": "sdd_clients_crm_regras_de_neg_cio", "label": "Regras de Neg\u00f3cio", "file_type": "document", "source_file": "C:\\Users\\User\\Downloads\\Rhian-Lepore-main\\_reversa_sdd\\sdd\\clients-crm.md", "source_location": "L45"}, {"id": "sdd_clients_crm_fluxo_principal", "label": "Fluxo Principal", "file_type": "document", "source_file": "C:\\Users\\User\\Downloads\\Rhian-Lepore-main\\_reversa_sdd\\sdd\\clients-crm.md", "source_location": "L59"}, {"id": "sdd_clients_crm_sincroniza_o_de_clientes_p_blicos", "label": "Sincroniza\u00e7\u00e3o de Clientes P\u00fablicos", "file_type": "document", "source_file": "C:\\Users\\User\\Downloads\\Rhian-Lepore-main\\_reversa_sdd\\sdd\\clients-crm.md", "source_location": "L61"}, {"id": "sdd_clients_crm_cria_o_manual_de_cliente", "label": "Cria\u00e7\u00e3o Manual de Cliente", "file_type": "document", "source_file": "C:\\Users\\User\\Downloads\\Rhian-Lepore-main\\_reversa_sdd\\sdd\\clients-crm.md", "source_location": "L73"}, {"id": "sdd_clients_crm_perfil_do_cliente_clientcrm", "label": "Perfil do Cliente (ClientCRM)", "file_type": "document", "source_file": "C:\\Users\\User\\Downloads\\Rhian-Lepore-main\\_reversa_sdd\\sdd\\clients-crm.md", "source_location": "L83"}, {"id": "sdd_clients_crm_portal_do_cliente_clientarea", "label": "Portal do Cliente (ClientArea)", "file_type": "document", "source_file": "C:\\Users\\User\\Downloads\\Rhian-Lepore-main\\_reversa_sdd\\sdd\\clients-crm.md", "source_location": "L91"}, {"id": "sdd_clients_crm_mem_ria_sem_ntica", "label": "Mem\u00f3ria Sem\u00e2ntica", "file_type": "document", "source_file": "C:\\Users\\User\\Downloads\\Rhian-Lepore-main\\_reversa_sdd\\sdd\\clients-crm.md", "source_location": "L106"}, {"id": "sdd_clients_crm_fluxos_alternativos", "label": "Fluxos Alternativos", "file_type": "document", "source_file": "C:\\Users\\User\\Downloads\\Rhian-Lepore-main\\_reversa_sdd\\sdd\\clients-crm.md", "source_location": "L114"}, {"id": "sdd_clients_crm_cen_rios_de_borda", "label": "Cen\u00e1rios de Borda", "file_type": "document", "source_file": "C:\\Users\\User\\Downloads\\Rhian-Lepore-main\\_reversa_sdd\\sdd\\clients-crm.md", "source_location": "L121"}, {"id": "sdd_clients_crm_b1_sincroniza_o_cria_cliente_duplicado_se_telefone_mudou", "label": "B1 \u2014 Sincroniza\u00e7\u00e3o cria cliente duplicado se telefone mudou", "file_type": "document", "source_file": "C:\\Users\\User\\Downloads\\Rhian-Lepore-main\\_reversa_sdd\\sdd\\clients-crm.md", "source_location": "L123"}, {"id": "sdd_clients_crm_b2_mem_ria_sem_ntica_cresce_indefinidamente_resolvido", "label": "B2 \u2014 Mem\u00f3ria sem\u00e2ntica cresce indefinidamente (Resolvido)", "file_type": "document", "source_file": "C:\\Users\\User\\Downloads\\Rhian-Lepore-main\\_reversa_sdd\\sdd\\clients-crm.md", "source_location": "L129"}, {"id": "sdd_clients_crm_b3_cliente_com_visitas_insuficientes_para_previs_o", "label": "B3 \u2014 Cliente com visitas insuficientes para previs\u00e3o", "file_type": "document", "source_file": "C:\\Users\\User\\Downloads\\Rhian-Lepore-main\\_reversa_sdd\\sdd\\clients-crm.md", "source_location": "L136"}, {"id": "sdd_clients_crm_depend_ncias", "label": "Depend\u00eancias", "file_type": "document", "source_file": "C:\\Users\\User\\Downloads\\Rhian-Lepore-main\\_reversa_sdd\\sdd\\clients-crm.md", "source_location": "L142"}, {"id": "sdd_clients_crm_requisitos_n_o_funcionais", "label": "Requisitos N\u00e3o Funcionais", "file_type": "document", "source_file": "C:\\Users\\User\\Downloads\\Rhian-Lepore-main\\_reversa_sdd\\sdd\\clients-crm.md", "source_location": "L153"}, {"id": "sdd_clients_crm_crit_rios_de_aceita_o", "label": "Crit\u00e9rios de Aceita\u00e7\u00e3o", "file_type": "document", "source_file": "C:\\Users\\User\\Downloads\\Rhian-Lepore-main\\_reversa_sdd\\sdd\\clients-crm.md", "source_location": "L161"}, {"id": "sdd_clients_crm_codeblock_1", "label": "code:gherkin (# Cen\u00e1rio 1: Sincronizar clientes p\u00fablicos)", "file_type": "document", "source_file": "C:\\Users\\User\\Downloads\\Rhian-Lepore-main\\_reversa_sdd\\sdd\\clients-crm.md", "source_location": "L163"}, {"id": "sdd_clients_crm_prioridade", "label": "Prioridade", "file_type": "document", "source_file": "C:\\Users\\User\\Downloads\\Rhian-Lepore-main\\_reversa_sdd\\sdd\\clients-crm.md", "source_location": "L189"}, {"id": "sdd_clients_crm_rastreabilidade_de_c_digo", "label": "Rastreabilidade de C\u00f3digo", "file_type": "document", "source_file": "C:\\Users\\User\\Downloads\\Rhian-Lepore-main\\_reversa_sdd\\sdd\\clients-crm.md", "source_location": "L200"}], "edges": [{"source": "c_users_user_downloads_rhian_lepore_main_reversa_sdd_sdd_clients_crm_md", "target": "sdd_clients_crm_clientes_e_crm_clients_crm", "relation": "contains", "confidence": "EXTRACTED", "source_file": "C:\\Users\\User\\Downloads\\Rhian-Lepore-main\\_reversa_sdd\\sdd\\clients-crm.md", "source_location": "L1", "weight": 1.0}, {"source": "sdd_clients_crm_clientes_e_crm_clients_crm", "target": "sdd_clients_crm_vis_o_geral", "relation": "contains", "confidence": "EXTRACTED", "source_file": "C:\\Users\\User\\Downloads\\Rhian-Lepore-main\\_reversa_sdd\\sdd\\clients-crm.md", "source_location": "L3", "weight": 1.0}, {"source": "sdd_clients_crm_clientes_e_crm_clients_crm", "target": "sdd_clients_crm_responsabilidades", "relation": "contains", "confidence": "EXTRACTED", "source_file": "C:\\Users\\User\\Downloads\\Rhian-Lepore-main\\_reversa_sdd\\sdd\\clients-crm.md", "source_location": "L6", "weight": 1.0}, {"source": "sdd_clients_crm_clientes_e_crm_clients_crm", "target": "sdd_clients_crm_interface", "relation": "contains", "confidence": "EXTRACTED", "source_file": "C:\\Users\\User\\Downloads\\Rhian-Lepore-main\\_reversa_sdd\\sdd\\clients-crm.md", "source_location": "L19", "weight": 1.0}, {"source": "sdd_clients_crm_interface", "target": "sdd_clients_crm_entradas", "relation": "contains", "confidence": "EXTRACTED", "source_file": "C:\\Users\\User\\Downloads\\Rhian-Lepore-main\\_reversa_sdd\\sdd\\clients-crm.md", "source_location": "L21", "weight": 1.0}, {"source": "sdd_clients_crm_interface", "target": "sdd_clients_crm_sa_das", "relation": "contains", "confidence": "EXTRACTED", "source_file": "C:\\Users\\User\\Downloads\\Rhian-Lepore-main\\_reversa_sdd\\sdd\\clients-crm.md", "source_location": "L34", "weight": 1.0}, {"source": "sdd_clients_crm_clientes_e_crm_clients_crm", "target": "sdd_clients_crm_regras_de_neg_cio", "relation": "contains", "confidence": "EXTRACTED", "source_file": "C:\\Users\\User\\Downloads\\Rhian-Lepore-main\\_reversa_sdd\\sdd\\clients-crm.md", "source_location": "L45", "weight": 1.0}, {"source": "sdd_clients_crm_clientes_e_crm_clients_crm", "target": "sdd_clients_crm_fluxo_principal", "relation": "contains", "confidence": "EXTRACTED", "source_file": "C:\\Users\\User\\Downloads\\Rhian-Lepore-main\\_reversa_sdd\\sdd\\clients-crm.md", "source_location": "L59", "weight": 1.0}, {"source": "sdd_clients_crm_fluxo_principal", "target": "sdd_clients_crm_sincroniza_o_de_clientes_p_blicos", "relation": "contains", "confidence": "EXTRACTED", "source_file": "C:\\Users\\User\\Downloads\\Rhian-Lepore-main\\_reversa_sdd\\sdd\\clients-crm.md", "source_location": "L61", "weight": 1.0}, {"source": "sdd_clients_crm_fluxo_principal", "target": "sdd_clients_crm_cria_o_manual_de_cliente", "relation": "contains", "confidence": "EXTRACTED", "source_file": "C:\\Users\\User\\Downloads\\Rhian-Lepore-main\\_reversa_sdd\\sdd\\clients-crm.md", "source_location": "L73", "weight": 1.0}, {"source": "sdd_clients_crm_fluxo_principal", "target": "sdd_clients_crm_perfil_do_cliente_clientcrm", "relation": "contains", "confidence": "EXTRACTED", "source_file": "C:\\Users\\User\\Downloads\\Rhian-Lepore-main\\_reversa_sdd\\sdd\\clients-crm.md", "source_location": "L83", "weight": 1.0}, {"source": "sdd_clients_crm_fluxo_principal", "target": "sdd_clients_crm_portal_do_cliente_clientarea", "relation": "contains", "confidence": "EXTRACTED", "source_file": "C:\\Users\\User\\Downloads\\Rhian-Lepore-main\\_reversa_sdd\\sdd\\clients-crm.md", "source_location": "L91", "weight": 1.0}, {"source": "sdd_clients_crm_fluxo_principal", "target": "sdd_clients_crm_mem_ria_sem_ntica", "relation": "contains", "confidence": "EXTRACTED", "source_file": "C:\\Users\\User\\Downloads\\Rhian-Lepore-main\\_reversa_sdd\\sdd\\clients-crm.md", "source_location": "L106", "weight": 1.0}, {"source": "sdd_clients_crm_clientes_e_crm_clients_crm", "target": "sdd_clients_crm_fluxos_alternativos", "relation": "contains", "confidence": "EXTRACTED", "source_file": "C:\\Users\\User\\Downloads\\Rhian-Lepore-main\\_reversa_sdd\\sdd\\clients-crm.md", "source_location": "L114", "weight": 1.0}, {"source": "sdd_clients_crm_clientes_e_crm_clients_crm", "target": "sdd_clients_crm_cen_rios_de_borda", "relation": "contains", "confidence": "EXTRACTED", "source_file": "C:\\Users\\User\\Downloads\\Rhian-Lepore-main\\_reversa_sdd\\sdd\\clients-crm.md", "source_location": "L121", "weight": 1.0}, {"source": "sdd_clients_crm_cen_rios_de_borda", "target": "sdd_clients_crm_b1_sincroniza_o_cria_cliente_duplicado_se_telefone_mudou", "relation": "contains", "confidence": "EXTRACTED", "source_file": "C:\\Users\\User\\Downloads\\Rhian-Lepore-main\\_reversa_sdd\\sdd\\clients-crm.md", "source_location": "L123", "weight": 1.0}, {"source": "sdd_clients_crm_cen_rios_de_borda", "target": "sdd_clients_crm_b2_mem_ria_sem_ntica_cresce_indefinidamente_resolvido", "relation": "contains", "confidence": "EXTRACTED", "source_file": "C:\\Users\\User\\Downloads\\Rhian-Lepore-main\\_reversa_sdd\\sdd\\clients-crm.md", "source_location": "L129", "weight": 1.0}, {"source": "sdd_clients_crm_cen_rios_de_borda", "target": "sdd_clients_crm_b3_cliente_com_visitas_insuficientes_para_previs_o", "relation": "contains", "confidence": "EXTRACTED", "source_file": "C:\\Users\\User\\Downloads\\Rhian-Lepore-main\\_reversa_sdd\\sdd\\clients-crm.md", "source_location": "L136", "weight": 1.0}, {"source": "sdd_clients_crm_clientes_e_crm_clients_crm", "target": "sdd_clients_crm_depend_ncias", "relation": "contains", "confidence": "EXTRACTED", "source_file": "C:\\Users\\User\\Downloads\\Rhian-Lepore-main\\_reversa_sdd\\sdd\\clients-crm.md", "source_location": "L142", "weight": 1.0}, {"source": "sdd_clients_crm_clientes_e_crm_clients_crm", "target": "sdd_clients_crm_requisitos_n_o_funcionais", "relation": "contains", "confidence": "EXTRACTED", "source_file": "C:\\Users\\User\\Downloads\\Rhian-Lepore-main\\_reversa_sdd\\sdd\\clients-crm.md", "source_location": "L153", "weight": 1.0}, {"source": "sdd_clients_crm_clientes_e_crm_clients_crm", "target": "sdd_clients_crm_crit_rios_de_aceita_o", "relation": "contains", "confidence": "EXTRACTED", "source_file": "C:\\Users\\User\\Downloads\\Rhian-Lepore-main\\_reversa_sdd\\sdd\\clients-crm.md", "source_location": "L161", "weight": 1.0}, {"source": "sdd_clients_crm_crit_rios_de_aceita_o", "target": "sdd_clients_crm_codeblock_1", "relation": "contains", "confidence": "EXTRACTED", "source_file": "C:\\Users\\User\\Downloads\\Rhian-Lepore-main\\_reversa_sdd\\sdd\\clients-crm.md", "source_location": "L163", "weight": 1.0}, {"source": "sdd_clients_crm_clientes_e_crm_clients_crm", "target": "sdd_clients_crm_prioridade", "relation": "contains", "confidence": "EXTRACTED", "source_file": "C:\\Users\\User\\Downloads\\Rhian-Lepore-main\\_reversa_sdd\\sdd\\clients-crm.md", "source_location": "L189", "weight": 1.0}, {"source": "sdd_clients_crm_clientes_e_crm_clients_crm", "target": "sdd_clients_crm_rastreabilidade_de_c_digo", "relation": "contains", "confidence": "EXTRACTED", "source_file": "C:\\Users\\User\\Downloads\\Rhian-Lepore-main\\_reversa_sdd\\sdd\\clients-crm.md", "source_location": "L200", "weight": 1.0}], "input_tokens": 0, "output_tokens": 0}