{"nodes": [{"id": "c_users_user_downloads_rhian_lepore_main_reversa_sdd_migration_target_domain_model_md", "label": "target_domain_model.md", "file_type": "document", "source_file": "C:\\Users\\User\\Downloads\\Rhian-Lepore-main\\_reversa_sdd\\migration\\target_domain_model.md", "source_location": "L1"}, {"id": "migration_target_domain_model_target_domain_model", "label": "Target Domain Model", "file_type": "document", "source_file": "C:\\Users\\User\\Downloads\\Rhian-Lepore-main\\_reversa_sdd\\migration\\target_domain_model.md", "source_location": "L10"}, {"id": "migration_target_domain_model_bc_1_identity", "label": "BC-1: Identity", "file_type": "document", "source_file": "C:\\Users\\User\\Downloads\\Rhian-Lepore-main\\_reversa_sdd\\migration\\target_domain_model.md", "source_location": "L16"}, {"id": "migration_target_domain_model_aggregates", "label": "Aggregates", "file_type": "document", "source_file": "C:\\Users\\User\\Downloads\\Rhian-Lepore-main\\_reversa_sdd\\migration\\target_domain_model.md", "source_location": "L18"}, {"id": "migration_target_domain_model_profile_root", "label": "Profile (root)", "file_type": "document", "source_file": "C:\\Users\\User\\Downloads\\Rhian-Lepore-main\\_reversa_sdd\\migration\\target_domain_model.md", "source_location": "L20"}, {"id": "migration_target_domain_model_onboarding_root", "label": "Onboarding (root)", "file_type": "document", "source_file": "C:\\Users\\User\\Downloads\\Rhian-Lepore-main\\_reversa_sdd\\migration\\target_domain_model.md", "source_location": "L27"}, {"id": "migration_target_domain_model_regras_de_dominio", "label": "Regras de dominio", "file_type": "document", "source_file": "C:\\Users\\User\\Downloads\\Rhian-Lepore-main\\_reversa_sdd\\migration\\target_domain_model.md", "source_location": "L34"}, {"id": "migration_target_domain_model_bc_2_scheduling", "label": "BC-2: Scheduling", "file_type": "document", "source_file": "C:\\Users\\User\\Downloads\\Rhian-Lepore-main\\_reversa_sdd\\migration\\target_domain_model.md", "source_location": "L54"}, {"id": "migration_target_domain_model_aggregates_56", "label": "Aggregates", "file_type": "document", "source_file": "C:\\Users\\User\\Downloads\\Rhian-Lepore-main\\_reversa_sdd\\migration\\target_domain_model.md", "source_location": "L56"}, {"id": "migration_target_domain_model_appointment_root", "label": "Appointment (root)", "file_type": "document", "source_file": "C:\\Users\\User\\Downloads\\Rhian-Lepore-main\\_reversa_sdd\\migration\\target_domain_model.md", "source_location": "L58"}, {"id": "migration_target_domain_model_regras_de_dominio_65", "label": "Regras de dominio", "file_type": "document", "source_file": "C:\\Users\\User\\Downloads\\Rhian-Lepore-main\\_reversa_sdd\\migration\\target_domain_model.md", "source_location": "L65"}, {"id": "migration_target_domain_model_bc_3_public_booking", "label": "BC-3: Public Booking", "file_type": "document", "source_file": "C:\\Users\\User\\Downloads\\Rhian-Lepore-main\\_reversa_sdd\\migration\\target_domain_model.md", "source_location": "L82"}, {"id": "migration_target_domain_model_aggregates_84", "label": "Aggregates", "file_type": "document", "source_file": "C:\\Users\\User\\Downloads\\Rhian-Lepore-main\\_reversa_sdd\\migration\\target_domain_model.md", "source_location": "L84"}, {"id": "migration_target_domain_model_publicbooking_root", "label": "PublicBooking (root)", "file_type": "document", "source_file": "C:\\Users\\User\\Downloads\\Rhian-Lepore-main\\_reversa_sdd\\migration\\target_domain_model.md", "source_location": "L86"}, {"id": "migration_target_domain_model_regras_de_dominio_93", "label": "Regras de dominio", "file_type": "document", "source_file": "C:\\Users\\User\\Downloads\\Rhian-Lepore-main\\_reversa_sdd\\migration\\target_domain_model.md", "source_location": "L93"}, {"id": "migration_target_domain_model_bc_4_queue", "label": "BC-4: Queue", "file_type": "document", "source_file": "C:\\Users\\User\\Downloads\\Rhian-Lepore-main\\_reversa_sdd\\migration\\target_domain_model.md", "source_location": "L105"}, {"id": "migration_target_domain_model_aggregates_107", "label": "Aggregates", "file_type": "document", "source_file": "C:\\Users\\User\\Downloads\\Rhian-Lepore-main\\_reversa_sdd\\migration\\target_domain_model.md", "source_location": "L107"}, {"id": "migration_target_domain_model_queueentry_root", "label": "QueueEntry (root)", "file_type": "document", "source_file": "C:\\Users\\User\\Downloads\\Rhian-Lepore-main\\_reversa_sdd\\migration\\target_domain_model.md", "source_location": "L109"}, {"id": "migration_target_domain_model_regras_de_dominio_116", "label": "Regras de dominio", "file_type": "document", "source_file": "C:\\Users\\User\\Downloads\\Rhian-Lepore-main\\_reversa_sdd\\migration\\target_domain_model.md", "source_location": "L116"}, {"id": "migration_target_domain_model_bc_5_finance", "label": "BC-5: Finance", "file_type": "document", "source_file": "C:\\Users\\User\\Downloads\\Rhian-Lepore-main\\_reversa_sdd\\migration\\target_domain_model.md", "source_location": "L130"}, {"id": "migration_target_domain_model_aggregates_132", "label": "Aggregates", "file_type": "document", "source_file": "C:\\Users\\User\\Downloads\\Rhian-Lepore-main\\_reversa_sdd\\migration\\target_domain_model.md", "source_location": "L132"}, {"id": "migration_target_domain_model_financerecord_root", "label": "FinanceRecord (root)", "file_type": "document", "source_file": "C:\\Users\\User\\Downloads\\Rhian-Lepore-main\\_reversa_sdd\\migration\\target_domain_model.md", "source_location": "L134"}, {"id": "migration_target_domain_model_commission_root", "label": "Commission (root)", "file_type": "document", "source_file": "C:\\Users\\User\\Downloads\\Rhian-Lepore-main\\_reversa_sdd\\migration\\target_domain_model.md", "source_location": "L141"}, {"id": "migration_target_domain_model_regras_de_dominio_148", "label": "Regras de dominio", "file_type": "document", "source_file": "C:\\Users\\User\\Downloads\\Rhian-Lepore-main\\_reversa_sdd\\migration\\target_domain_model.md", "source_location": "L148"}, {"id": "migration_target_domain_model_bc_6_crm", "label": "BC-6: CRM", "file_type": "document", "source_file": "C:\\Users\\User\\Downloads\\Rhian-Lepore-main\\_reversa_sdd\\migration\\target_domain_model.md", "source_location": "L169"}, {"id": "migration_target_domain_model_aggregates_171", "label": "Aggregates", "file_type": "document", "source_file": "C:\\Users\\User\\Downloads\\Rhian-Lepore-main\\_reversa_sdd\\migration\\target_domain_model.md", "source_location": "L171"}, {"id": "migration_target_domain_model_client_root", "label": "Client (root)", "file_type": "document", "source_file": "C:\\Users\\User\\Downloads\\Rhian-Lepore-main\\_reversa_sdd\\migration\\target_domain_model.md", "source_location": "L173"}, {"id": "migration_target_domain_model_regras_de_dominio_180", "label": "Regras de dominio", "file_type": "document", "source_file": "C:\\Users\\User\\Downloads\\Rhian-Lepore-main\\_reversa_sdd\\migration\\target_domain_model.md", "source_location": "L180"}, {"id": "migration_target_domain_model_bc_7_team", "label": "BC-7: Team", "file_type": "document", "source_file": "C:\\Users\\User\\Downloads\\Rhian-Lepore-main\\_reversa_sdd\\migration\\target_domain_model.md", "source_location": "L189"}, {"id": "migration_target_domain_model_aggregates_191", "label": "Aggregates", "file_type": "document", "source_file": "C:\\Users\\User\\Downloads\\Rhian-Lepore-main\\_reversa_sdd\\migration\\target_domain_model.md", "source_location": "L191"}, {"id": "migration_target_domain_model_teammember_root", "label": "TeamMember (root)", "file_type": "document", "source_file": "C:\\Users\\User\\Downloads\\Rhian-Lepore-main\\_reversa_sdd\\migration\\target_domain_model.md", "source_location": "L193"}, {"id": "migration_target_domain_model_bc_8_catalog", "label": "BC-8: Catalog", "file_type": "document", "source_file": "C:\\Users\\User\\Downloads\\Rhian-Lepore-main\\_reversa_sdd\\migration\\target_domain_model.md", "source_location": "L202"}, {"id": "migration_target_domain_model_aggregates_204", "label": "Aggregates", "file_type": "document", "source_file": "C:\\Users\\User\\Downloads\\Rhian-Lepore-main\\_reversa_sdd\\migration\\target_domain_model.md", "source_location": "L204"}, {"id": "migration_target_domain_model_service_root", "label": "Service (root)", "file_type": "document", "source_file": "C:\\Users\\User\\Downloads\\Rhian-Lepore-main\\_reversa_sdd\\migration\\target_domain_model.md", "source_location": "L206"}, {"id": "migration_target_domain_model_product_root_novo_na_v1", "label": "Product (root) -- NOVO na v1", "file_type": "document", "source_file": "C:\\Users\\User\\Downloads\\Rhian-Lepore-main\\_reversa_sdd\\migration\\target_domain_model.md", "source_location": "L212"}, {"id": "migration_target_domain_model_bc_9_observability", "label": "BC-9: Observability", "file_type": "document", "source_file": "C:\\Users\\User\\Downloads\\Rhian-Lepore-main\\_reversa_sdd\\migration\\target_domain_model.md", "source_location": "L222"}, {"id": "migration_target_domain_model_rastreabilidade_para_legado", "label": "Rastreabilidade para legado", "file_type": "document", "source_file": "C:\\Users\\User\\Downloads\\Rhian-Lepore-main\\_reversa_sdd\\migration\\target_domain_model.md", "source_location": "L231"}], "edges": [{"source": "c_users_user_downloads_rhian_lepore_main_reversa_sdd_migration_target_domain_model_md", "target": "migration_target_domain_model_target_domain_model", "relation": "contains", "confidence": "EXTRACTED", "source_file": "C:\\Users\\User\\Downloads\\Rhian-Lepore-main\\_reversa_sdd\\migration\\target_domain_model.md", "source_location": "L10", "weight": 1.0}, {"source": "migration_target_domain_model_target_domain_model", "target": "migration_target_domain_model_bc_1_identity", "relation": "contains", "confidence": "EXTRACTED", "source_file": "C:\\Users\\User\\Downloads\\Rhian-Lepore-main\\_reversa_sdd\\migration\\target_domain_model.md", "source_location": "L16", "weight": 1.0}, {"source": "migration_target_domain_model_bc_1_identity", "target": "migration_target_domain_model_aggregates", "relation": "contains", "confidence": "EXTRACTED", "source_file": "C:\\Users\\User\\Downloads\\Rhian-Lepore-main\\_reversa_sdd\\migration\\target_domain_model.md", "source_location": "L18", "weight": 1.0}, {"source": "migration_target_domain_model_aggregates", "target": "migration_target_domain_model_profile_root", "relation": "contains", "confidence": "EXTRACTED", "source_file": "C:\\Users\\User\\Downloads\\Rhian-Lepore-main\\_reversa_sdd\\migration\\target_domain_model.md", "source_location": "L20", "weight": 1.0}, {"source": "migration_target_domain_model_aggregates", "target": "migration_target_domain_model_onboarding_root", "relation": "contains", "confidence": "EXTRACTED", "source_file": "C:\\Users\\User\\Downloads\\Rhian-Lepore-main\\_reversa_sdd\\migration\\target_domain_model.md", "source_location": "L27", "weight": 1.0}, {"source": "migration_target_domain_model_bc_1_identity", "target": "migration_target_domain_model_regras_de_dominio", "relation": "contains", "confidence": "EXTRACTED", "source_file": "C:\\Users\\User\\Downloads\\Rhian-Lepore-main\\_reversa_sdd\\migration\\target_domain_model.md", "source_location": "L34", "weight": 1.0}, {"source": "migration_target_domain_model_target_domain_model", "target": "migration_target_domain_model_bc_2_scheduling", "relation": "contains", "confidence": "EXTRACTED", "source_file": "C:\\Users\\User\\Downloads\\Rhian-Lepore-main\\_reversa_sdd\\migration\\target_domain_model.md", "source_location": "L54", "weight": 1.0}, {"source": "migration_target_domain_model_bc_2_scheduling", "target": "migration_target_domain_model_aggregates_56", "relation": "contains", "confidence": "EXTRACTED", "source_file": "C:\\Users\\User\\Downloads\\Rhian-Lepore-main\\_reversa_sdd\\migration\\target_domain_model.md", "source_location": "L56", "weight": 1.0}, {"source": "migration_target_domain_model_aggregates_56", "target": "migration_target_domain_model_appointment_root", "relation": "contains", "confidence": "EXTRACTED", "source_file": "C:\\Users\\User\\Downloads\\Rhian-Lepore-main\\_reversa_sdd\\migration\\target_domain_model.md", "source_location": "L58", "weight": 1.0}, {"source": "migration_target_domain_model_bc_2_scheduling", "target": "migration_target_domain_model_regras_de_dominio_65", "relation": "contains", "confidence": "EXTRACTED", "source_file": "C:\\Users\\User\\Downloads\\Rhian-Lepore-main\\_reversa_sdd\\migration\\target_domain_model.md", "source_location": "L65", "weight": 1.0}, {"source": "migration_target_domain_model_target_domain_model", "target": "migration_target_domain_model_bc_3_public_booking", "relation": "contains", "confidence": "EXTRACTED", "source_file": "C:\\Users\\User\\Downloads\\Rhian-Lepore-main\\_reversa_sdd\\migration\\target_domain_model.md", "source_location": "L82", "weight": 1.0}, {"source": "migration_target_domain_model_bc_3_public_booking", "target": "migration_target_domain_model_aggregates_84", "relation": "contains", "confidence": "EXTRACTED", "source_file": "C:\\Users\\User\\Downloads\\Rhian-Lepore-main\\_reversa_sdd\\migration\\target_domain_model.md", "source_location": "L84", "weight": 1.0}, {"source": "migration_target_domain_model_aggregates_84", "target": "migration_target_domain_model_publicbooking_root", "relation": "contains", "confidence": "EXTRACTED", "source_file": "C:\\Users\\User\\Downloads\\Rhian-Lepore-main\\_reversa_sdd\\migration\\target_domain_model.md", "source_location": "L86", "weight": 1.0}, {"source": "migration_target_domain_model_bc_3_public_booking", "target": "migration_target_domain_model_regras_de_dominio_93", "relation": "contains", "confidence": "EXTRACTED", "source_file": "C:\\Users\\User\\Downloads\\Rhian-Lepore-main\\_reversa_sdd\\migration\\target_domain_model.md", "source_location": "L93", "weight": 1.0}, {"source": "migration_target_domain_model_target_domain_model", "target": "migration_target_domain_model_bc_4_queue", "relation": "contains", "confidence": "EXTRACTED", "source_file": "C:\\Users\\User\\Downloads\\Rhian-Lepore-main\\_reversa_sdd\\migration\\target_domain_model.md", "source_location": "L105", "weight": 1.0}, {"source": "migration_target_domain_model_bc_4_queue", "target": "migration_target_domain_model_aggregates_107", "relation": "contains", "confidence": "EXTRACTED", "source_file": "C:\\Users\\User\\Downloads\\Rhian-Lepore-main\\_reversa_sdd\\migration\\target_domain_model.md", "source_location": "L107", "weight": 1.0}, {"source": "migration_target_domain_model_aggregates_107", "target": "migration_target_domain_model_queueentry_root", "relation": "contains", "confidence": "EXTRACTED", "source_file": "C:\\Users\\User\\Downloads\\Rhian-Lepore-main\\_reversa_sdd\\migration\\target_domain_model.md", "source_location": "L109", "weight": 1.0}, {"source": "migration_target_domain_model_bc_4_queue", "target": "migration_target_domain_model_regras_de_dominio_116", "relation": "contains", "confidence": "EXTRACTED", "source_file": "C:\\Users\\User\\Downloads\\Rhian-Lepore-main\\_reversa_sdd\\migration\\target_domain_model.md", "source_location": "L116", "weight": 1.0}, {"source": "migration_target_domain_model_target_domain_model", "target": "migration_target_domain_model_bc_5_finance", "relation": "contains", "confidence": "EXTRACTED", "source_file": "C:\\Users\\User\\Downloads\\Rhian-Lepore-main\\_reversa_sdd\\migration\\target_domain_model.md", "source_location": "L130", "weight": 1.0}, {"source": "migration_target_domain_model_bc_5_finance", "target": "migration_target_domain_model_aggregates_132", "relation": "contains", "confidence": "EXTRACTED", "source_file": "C:\\Users\\User\\Downloads\\Rhian-Lepore-main\\_reversa_sdd\\migration\\target_domain_model.md", "source_location": "L132", "weight": 1.0}, {"source": "migration_target_domain_model_aggregates_132", "target": "migration_target_domain_model_financerecord_root", "relation": "contains", "confidence": "EXTRACTED", "source_file": "C:\\Users\\User\\Downloads\\Rhian-Lepore-main\\_reversa_sdd\\migration\\target_domain_model.md", "source_location": "L134", "weight": 1.0}, {"source": "migration_target_domain_model_aggregates_132", "target": "migration_target_domain_model_commission_root", "relation": "contains", "confidence": "EXTRACTED", "source_file": "C:\\Users\\User\\Downloads\\Rhian-Lepore-main\\_reversa_sdd\\migration\\target_domain_model.md", "source_location": "L141", "weight": 1.0}, {"source": "migration_target_domain_model_bc_5_finance", "target": "migration_target_domain_model_regras_de_dominio_148", "relation": "contains", "confidence": "EXTRACTED", "source_file": "C:\\Users\\User\\Downloads\\Rhian-Lepore-main\\_reversa_sdd\\migration\\target_domain_model.md", "source_location": "L148", "weight": 1.0}, {"source": "migration_target_domain_model_target_domain_model", "target": "migration_target_domain_model_bc_6_crm", "relation": "contains", "confidence": "EXTRACTED", "source_file": "C:\\Users\\User\\Downloads\\Rhian-Lepore-main\\_reversa_sdd\\migration\\target_domain_model.md", "source_location": "L169", "weight": 1.0}, {"source": "migration_target_domain_model_bc_6_crm", "target": "migration_target_domain_model_aggregates_171", "relation": "contains", "confidence": "EXTRACTED", "source_file": "C:\\Users\\User\\Downloads\\Rhian-Lepore-main\\_reversa_sdd\\migration\\target_domain_model.md", "source_location": "L171", "weight": 1.0}, {"source": "migration_target_domain_model_aggregates_171", "target": "migration_target_domain_model_client_root", "relation": "contains", "confidence": "EXTRACTED", "source_file": "C:\\Users\\User\\Downloads\\Rhian-Lepore-main\\_reversa_sdd\\migration\\target_domain_model.md", "source_location": "L173", "weight": 1.0}, {"source": "migration_target_domain_model_bc_6_crm", "target": "migration_target_domain_model_regras_de_dominio_180", "relation": "contains", "confidence": "EXTRACTED", "source_file": "C:\\Users\\User\\Downloads\\Rhian-Lepore-main\\_reversa_sdd\\migration\\target_domain_model.md", "source_location": "L180", "weight": 1.0}, {"source": "migration_target_domain_model_target_domain_model", "target": "migration_target_domain_model_bc_7_team", "relation": "contains", "confidence": "EXTRACTED", "source_file": "C:\\Users\\User\\Downloads\\Rhian-Lepore-main\\_reversa_sdd\\migration\\target_domain_model.md", "source_location": "L189", "weight": 1.0}, {"source": "migration_target_domain_model_bc_7_team", "target": "migration_target_domain_model_aggregates_191", "relation": "contains", "confidence": "EXTRACTED", "source_file": "C:\\Users\\User\\Downloads\\Rhian-Lepore-main\\_reversa_sdd\\migration\\target_domain_model.md", "source_location": "L191", "weight": 1.0}, {"source": "migration_target_domain_model_aggregates_191", "target": "migration_target_domain_model_teammember_root", "relation": "contains", "confidence": "EXTRACTED", "source_file": "C:\\Users\\User\\Downloads\\Rhian-Lepore-main\\_reversa_sdd\\migration\\target_domain_model.md", "source_location": "L193", "weight": 1.0}, {"source": "migration_target_domain_model_target_domain_model", "target": "migration_target_domain_model_bc_8_catalog", "relation": "contains", "confidence": "EXTRACTED", "source_file": "C:\\Users\\User\\Downloads\\Rhian-Lepore-main\\_reversa_sdd\\migration\\target_domain_model.md", "source_location": "L202", "weight": 1.0}, {"source": "migration_target_domain_model_bc_8_catalog", "target": "migration_target_domain_model_aggregates_204", "relation": "contains", "confidence": "EXTRACTED", "source_file": "C:\\Users\\User\\Downloads\\Rhian-Lepore-main\\_reversa_sdd\\migration\\target_domain_model.md", "source_location": "L204", "weight": 1.0}, {"source": "migration_target_domain_model_aggregates_204", "target": "migration_target_domain_model_service_root", "relation": "contains", "confidence": "EXTRACTED", "source_file": "C:\\Users\\User\\Downloads\\Rhian-Lepore-main\\_reversa_sdd\\migration\\target_domain_model.md", "source_location": "L206", "weight": 1.0}, {"source": "migration_target_domain_model_aggregates_204", "target": "migration_target_domain_model_product_root_novo_na_v1", "relation": "contains", "confidence": "EXTRACTED", "source_file": "C:\\Users\\User\\Downloads\\Rhian-Lepore-main\\_reversa_sdd\\migration\\target_domain_model.md", "source_location": "L212", "weight": 1.0}, {"source": "migration_target_domain_model_target_domain_model", "target": "migration_target_domain_model_bc_9_observability", "relation": "contains", "confidence": "EXTRACTED", "source_file": "C:\\Users\\User\\Downloads\\Rhian-Lepore-main\\_reversa_sdd\\migration\\target_domain_model.md", "source_location": "L222", "weight": 1.0}, {"source": "migration_target_domain_model_target_domain_model", "target": "migration_target_domain_model_rastreabilidade_para_legado", "relation": "contains", "confidence": "EXTRACTED", "source_file": "C:\\Users\\User\\Downloads\\Rhian-Lepore-main\\_reversa_sdd\\migration\\target_domain_model.md", "source_location": "L231", "weight": 1.0}], "input_tokens": 0, "output_tokens": 0}