{"nodes": [{"id": "c_users_user_downloads_rhian_lepore_main_scripts_capture_v3_ts", "label": "capture-v3.ts", "file_type": "code", "source_file": "C:\\Users\\User\\Downloads\\Rhian-Lepore-main\\scripts\\capture-v3.ts", "source_location": "L1"}], "edges": [{"source": "c_users_user_downloads_rhian_lepore_main_scripts_capture_v3_ts", "target": "test", "relation": "imports_from", "context": "import", "confidence": "EXTRACTED", "source_file": "C:\\Users\\User\\Downloads\\Rhian-Lepore-main\\scripts\\capture-v3.ts", "source_location": "L1", "weight": 1.0}], "raw_calls": []}